{"_type":"export","__export_format":4,"__export_date":"2022-10-20T20:15:02.082Z","__export_source":"insomnia.desktop.app:v2022.6.0","resources":[{"_id":"req_8141fdbed43843e19ccfb1db79256c89","parentId":"wrk_8ff2eb2ba8034e9a9b1bb310922dd67d","modified":1666296831466,"created":1666261112378,"url":"http://localhost:3000/phases/e32bf507-b888-4035-9815-4b59594474c2/task/d9467e99-ee56-4e9e-8881-1bebdb8f2229/done/true","name":"Mark task as done","description":"","method":"PUT","body":{},"parameters":[],"headers":[],"authentication":{},"metaSortKey":-1666261112378,"isPrivate":false,"settingStoreCookies":true,"settingSendCookies":true,"settingDisableRenderRequestBody":false,"settingEncodeUrl":true,"settingRebuildPath":true,"settingFollowRedirects":"global","_type":"request"},{"_id":"wrk_8ff2eb2ba8034e9a9b1bb310922dd67d","parentId":null,"modified":1666087022300,"created":1666087022300,"name":"New Document","description":"","scope":"design","_type":"workspace"},{"_id":"req_22f47c28af9f4aa69128dfd08086c115","parentId":"wrk_8ff2eb2ba8034e9a9b1bb310922dd67d","modified":1666296814442,"created":1666179399424,"url":"http://localhost:3000/phases/e32bf507-b888-4035-9815-4b59594474c2/task","name":"Create Task","description":"","method":"POST","body":{"mimeType":"application/json","text":"{\n\t\"name\": \"task in another phase\",\n\t\"done\": false\n}"},"parameters":[],"headers":[{"name":"Content-Type","value":"application/json"}],"authentication":{},"metaSortKey":-1666179399424,"isPrivate":false,"settingStoreCookies":true,"settingSendCookies":true,"settingDisableRenderRequestBody":false,"settingEncodeUrl":true,"settingRebuildPath":true,"settingFollowRedirects":"global","_type":"request"},{"_id":"req_4af950c045224bcdb3c19ff4cbc42ac4","parentId":"wrk_8ff2eb2ba8034e9a9b1bb310922dd67d","modified":1666296809648,"created":1666087100469,"url":"http://localhost:3000/phases","name":"Request GraphQL data","description":"","method":"GET","body":{"mimeType":"application/graphql","text":"{\"query\":\"{\\n\\tphases {\\n\\t\\tname\\n\\t\\tid\\n\\t\\tdone\\n\\t\\ttasks {\\n\\t\\t\\tid\\n\\t\\t\\tname\\n\\t\\t\\tdone\\n\\t\\t}\\n\\t}\\n}\"}"},"parameters":[],"headers":[{"name":"Content-Type","value":"application/json"}],"authentication":{},"metaSortKey":-1666087100469,"isPrivate":false,"settingStoreCookies":true,"settingSendCookies":true,"settingDisableRenderRequestBody":false,"settingEncodeUrl":true,"settingRebuildPath":true,"settingFollowRedirects":"global","_type":"request"},{"_id":"req_ce54686b3b31431ea3e3722165675b53","parentId":"wrk_8ff2eb2ba8034e9a9b1bb310922dd67d","modified":1666296802533,"created":1666087022318,"url":"http://localhost:3000/phases","name":"Create Phase","description":"","method":"POST","body":{"mimeType":"application/json","text":"{\n\t\"name\": \"insominia 3\",\n\t\"done\": false\n}"},"parameters":[],"headers":[{"name":"Content-Type","value":"application/json","id":"pair_c2ee8108c4c74594a92e8e665c885d65"}],"authentication":{},"metaSortKey":-1666087022318,"isPrivate":false,"settingStoreCookies":true,"settingSendCookies":true,"settingDisableRenderRequestBody":false,"settingEncodeUrl":true,"settingRebuildPath":true,"settingFollowRedirects":"global","_type":"request"},{"_id":"env_e7023f3bc56881a32be822af5a337f06d6ca35de","parentId":"wrk_8ff2eb2ba8034e9a9b1bb310922dd67d","modified":1666087022314,"created":1666087022314,"name":"Base Environment","data":{},"dataPropertyOrder":null,"color":null,"isPrivate":false,"metaSortKey":1666087022314,"_type":"environment"},{"_id":"jar_e7023f3bc56881a32be822af5a337f06d6ca35de","parentId":"wrk_8ff2eb2ba8034e9a9b1bb310922dd67d","modified":1666087022316,"created":1666087022316,"name":"Default Jar","cookies":[],"_type":"cookie_jar"},{"_id":"spc_58cc1eaaa3f74903bed216e5f532d0b1","parentId":"wrk_8ff2eb2ba8034e9a9b1bb310922dd67d","modified":1666296848226,"created":1666087022311,"fileName":"GraphQL Project","contents":"","contentType":"yaml","_type":"api_spec"},{"_id":"uts_0752b02934324999b61345f2bc726326","parentId":"wrk_8ff2eb2ba8034e9a9b1bb310922dd67d","modified":1666087022319,"created":1666087022319,"name":"Example Test Suite","_type":"unit_test_suite"}]}